{"chunk_definitions":[{"chunk_id":"csetup_chunk","chunk_label":"setup","document_id":"91D74F4D","expansion_state":0,"options":{"engine":"r","include":false,"label":"setup"},"row":104,"row_count":1,"visible":true},{"chunk_id":"ckf2u5m9poktr","chunk_label":"analysis-preferences","document_id":"91D74F4D","expansion_state":0,"options":{"engine":"r","label":"analysis-preferences"},"row":110,"row_count":1,"visible":true},{"chunk_id":"c6n05efjftpa0","chunk_label":"read in data","document_id":"91D74F4D","expansion_state":0,"options":{"engine":"r","label":"read in data"},"row":137,"row_count":1,"visible":true},{"chunk_id":"ce644q4ntwtza","chunk_label":"participants","document_id":"91D74F4D","expansion_state":0,"options":{"engine":"r","label":"participants"},"row":158,"row_count":1,"visible":true},{"chunk_id":"cqf57d8u0i552","chunk_label":"missing_data_compare","document_id":"91D74F4D","expansion_state":0,"options":{"engine":"r","include":false,"label":"missing_data_compare"},"row":205,"row_count":1,"visible":true},{"chunk_id":"cpw1baes004kj","chunk_label":"demographics_1","document_id":"91D74F4D","expansion_state":0,"options":{"engine":"r","include":false,"label":"demographics_1"},"row":368,"row_count":1,"visible":true},{"chunk_id":"ckegj2rlc0n95","chunk_label":"descriptives_2_table","document_id":"91D74F4D","expansion_state":0,"options":{"engine":"r","label":"descriptives_2_table"},"row":412,"row_count":1,"visible":true},{"chunk_id":"cgh839v0rgd2u","chunk_label":"demographics_1_table","document_id":"91D74F4D","expansion_state":0,"options":{"engine":"r","label":"demographics_1_table"},"row":417,"row_count":1,"visible":true},{"chunk_id":"ct1lj7kdtdvbe","chunk_label":"demographics_sex","document_id":"91D74F4D","expansion_state":0,"options":{"engine":"r","label":"demographics_sex"},"row":424,"row_count":1,"visible":true},{"chunk_id":"czm595n1qyozh","chunk_label":"count_lowincome","document_id":"91D74F4D","expansion_state":0,"options":{"engine":"r","include":false,"label":"count_lowincome"},"row":433,"row_count":1,"visible":true},{"chunk_id":"cuhuk3irqk9fx","chunk_label":"interval","document_id":"91D74F4D","expansion_state":0,"options":{"engine":"r","label":"interval"},"row":453,"row_count":1,"visible":true},{"chunk_id":"ctu4n2cs13qqu","chunk_label":"tanner","document_id":"91D74F4D","expansion_state":0,"options":{"engine":"r","label":"tanner"},"row":466,"row_count":1,"visible":true},{"chunk_id":"cek8td3n4pwso","chunk_label":"included_ids","document_id":"91D74F4D","expansion_state":0,"options":{"engine":"r","label":"included_ids"},"row":477,"row_count":1,"visible":true},{"chunk_id":"c0xyhu3pb0yh7","chunk_label":"stress_table","document_id":"91D74F4D","expansion_state":0,"options":{"engine":"r","label":"stress_table"},"row":510,"row_count":1,"visible":true},{"chunk_id":"c1jx8q4po1qvv","chunk_label":"time_ttests","document_id":"91D74F4D","expansion_state":0,"options":{"engine":"r","label":"time_ttests"},"row":551,"row_count":1,"visible":true},{"chunk_id":"c7xop4z794ap6","chunk_label":"sex_differences","document_id":"91D74F4D","expansion_state":0,"options":{"engine":"r","label":"sex_differences"},"row":614,"row_count":1,"visible":true},{"chunk_id":"c1ipx9kxufms5","chunk_label":"medication_counts","document_id":"91D74F4D","expansion_state":0,"options":{"engine":"r","label":"medication_counts"},"row":634,"row_count":1,"visible":true},{"chunk_id":"ckrlp46w2n2bb","chunk_label":"correlations","document_id":"91D74F4D","expansion_state":0,"options":{"engine":"r","label":"unnamed-chunk-98"},"row":655,"row_count":1,"visible":true},{"chunk_id":"clqj7jyqy1i2j","chunk_label":"t1t2mod_modelfit","document_id":"91D74F4D","expansion_state":0,"options":{"engine":"r","include":false,"label":"t1t2mod_modelfit","warning":false},"row":790,"row_count":1,"visible":true},{"chunk_id":"clpdtq57o8owp","chunk_label":"t1t2mod","document_id":"91D74F4D","expansion_state":0,"options":{"engine":"r","include":false,"label":"t1t2mod","warning":false},"row":818,"row_count":1,"visible":true},{"chunk_id":"cexdnf647r8wq","chunk_label":"t1t2mod_sensitivity","document_id":"91D74F4D","expansion_state":0,"options":{"engine":"r","include":false,"label":"t1t2mod_sensitivity","warning":false},"row":835,"row_count":1,"visible":true},{"chunk_id":"c6l4quzwkgt60","chunk_label":"t1t2mod_corticosterid","document_id":"91D74F4D","expansion_state":0,"options":{"engine":"r","include":false,"label":"t1t2mod_corticosterid","warning":false},"row":855,"row_count":1,"visible":true},{"chunk_id":"cf1k9f0pscd5b","chunk_label":"t1t2mod_bysex","document_id":"91D74F4D","expansion_state":0,"options":{"engine":"r","include":false,"label":"t1t2mod_bysex","warning":false},"row":900,"row_count":1,"visible":true},{"chunk_id":"cqh05dceg6h5t","chunk_label":"plot_t1t2_mod","document_id":"91D74F4D","expansion_state":0,"options":{"engine":"r","label":"plot_t1t2_mod","warning":false},"row":938,"row_count":1,"visible":true},{"chunk_id":"cawsrv0a76bhf","chunk_label":"coupling_sensitivity","document_id":"91D74F4D","expansion_state":0,"options":{"engine":"r","include":false,"label":"coupling_sensitivity"},"row":1113,"row_count":1,"visible":true},{"chunk_id":"c6aae5t0nsndl","chunk_label":"coupling_threatcent","document_id":"91D74F4D","expansion_state":0,"options":{"engine":"r","label":"coupling_threatcent"},"row":1149,"row_count":1,"visible":true},{"chunk_id":"c3dzix8k6kiiw","chunk_label":"coupling_threatlo","document_id":"91D74F4D","expansion_state":0,"options":{"engine":"r","label":"coupling_threatlo"},"row":1180,"row_count":1,"visible":true},{"chunk_id":"cb9i75b7zunmt","chunk_label":"coupling_threathi","document_id":"91D74F4D","expansion_state":0,"options":{"engine":"r","label":"coupling_threathi"},"row":1211,"row_count":1,"visible":true},{"chunk_id":"c3jnaol55hxiq","chunk_label":"coupling_corticosteroid","document_id":"91D74F4D","expansion_state":0,"options":{"engine":"r","label":"coupling_corticosteroid"},"row":1254,"row_count":1,"visible":true},{"chunk_id":"cippobxvkw9es","chunk_label":"coupling_bysex","document_id":"91D74F4D","expansion_state":0,"options":{"engine":"r","label":"coupling_bysex"},"row":1321,"row_count":1,"visible":true},{"chunk_id":"cy9avy368v1pm","chunk_label":"plot_coupling_mod","document_id":"91D74F4D","expansion_state":0,"options":{"engine":"r","fig.height":3,"fig.width":6,"label":"plot_coupling_mod","warning":false},"row":1397,"row_count":1,"visible":true},{"chunk_id":"c1b78a05px16r","chunk_label":"coupling_inrcent","document_id":"91D74F4D","expansion_state":0,"options":{"engine":"r","label":"coupling_inrcent"},"row":1434,"row_count":1,"visible":true}],"default_chunk_options":{"error":false},"doc_write_time":1558225370,"working_dir":null}